[
    {
        "iconUrl": "",
        "apiVersion": 1,
        "repositoryUrl": "",
        "status": 1,
        "language": "en",
        "authors": [
            "test9"
        ],
        "tvTypes": [
            "AsianDrama",
            "TvSeries",
            "Anime",
            "Movie"
        ],
        "version": 228,
        "internalName": "SS",
        "description": "#SS MultiAPI",
        "url": "https://raw.githubusercontent.com/takkie9/takkie9.github.io/main/file/cs/ss.cs3",
        "name": "SS"
    },
    {
        "iconUrl": "https://www.google.com/s2/favicons?domain=185.231.223.76&sz=%size%",
        "apiVersion": 1,
        "repositoryUrl": "https://github.com/hexated/cloudstream-extensions-hexated",
        "fileSize": 17993,
        "status": 0,
        "language": "id",
        "authors": [
            "Hexated"
        ],
        "tvTypes": [
            "AnimeMovie",
            "Anime",
            "OVA"
        ],
        "version": 2,
        "internalName": "GomunimeProvider",
        "url": "https://raw.githubusercontent.com/hexated/cloudstream-extensions-hexated/builds/GomunimeProvider.cs3",
        "name": "GomunimeProvider"
    },
    {
        "iconUrl": "https://www.google.com/s2/favicons?domain=kissasian.pe&sz=%size%",
        "apiVersion": 1,
        "repositoryUrl": "https://github.com/hexated/cloudstream-extensions-hexated",
        "fileSize": 15984,
        "status": 1,
        "language": "en",
        "authors": [
            "Hexated"
        ],
        "tvTypes": [
            "AsianDrama"
        ],
        "version": 3,
        "internalName": "Kissasian",
        "description": "Include: KissasianMx",
        "url": "https://raw.githubusercontent.com/hexated/cloudstream-extensions-hexated/builds/Kissasian.cs3",
        "name": "Kissasian"
    },
    {
        "iconUrl": "https://www.google.com/s2/favicons?domain=kisskh.co&sz=%size%",
        "apiVersion": 1,
        "repositoryUrl": "https://github.com/hexated/cloudstream-extensions-hexated",
        "fileSize": 18803,
        "status": 1,
        "language": "en",
        "authors": [
            "Hexated"
        ],
        "tvTypes": [
            "AsianDrama",
            "TvSeries",
            "Anime",
            "Movie"
        ],
        "version": 4,
        "internalName": "KisskhProvider",
        "url": "https://raw.githubusercontent.com/hexated/cloudstream-extensions-hexated/builds/KisskhProvider.cs3",
        "name": "KisskhProvider"
    },
    {
        "iconUrl": "https://www.google.com/s2/favicons?domain=kuramanime.com&sz=%size%",
        "apiVersion": 1,
        "repositoryUrl": "https://github.com/hexated/cloudstream-extensions-hexated",
        "fileSize": 20276,
        "status": 1,
        "language": "id",
        "authors": [
            "Hexated"
        ],
        "tvTypes": [
            "AnimeMovie",
            "Anime",
            "OVA"
        ],
        "version": 39,
        "internalName": "KuramanimeProvider",
        "url": "https://raw.githubusercontent.com/hexated/cloudstream-extensions-hexated/builds/KuramanimeProvider.cs3",
        "name": "KuramanimeProvider"
    },
    {
        "iconUrl": "https://www.google.com/s2/favicons?domain=45.12.2.2&sz=%size%",
        "apiVersion": 1,
        "repositoryUrl": "https://github.com/hexated/cloudstream-extensions-hexated",
        "fileSize": 23612,
        "status": 1,
        "language": "id",
        "authors": [
            "Hexated"
        ],
        "tvTypes": [
            "AnimeMovie",
            "Anime",
            "OVA"
        ],
        "version": 20,
        "internalName": "KuronimeProvider",
        "url": "https://raw.githubusercontent.com/hexated/cloudstream-extensions-hexated/builds/KuronimeProvider.cs3",
        "name": "KuronimeProvider"
    }
]